{
	"spawns": [
		{
			"delay": {
				"seconds": 0.0
			},
			"patient": {
				"name": "John Somebody",
				"condition": "Infected Wound",
				"death_time": 100.0,
				"treatment_time": 10.0,
				"required_items": [
					"Antibiotic"
				]
			}
		},
		{
			"delay": {
				"seconds": 60.0
			},
			"patient": {
				"name": "Alice",
				"condition": "Allergic Reaction",
				"death_time": 100.0,
				"treatment_time": 10.0,
				"required_items": [
					"Oxygen Tank",
					"Inhalant"
				]
			}
		}
	]
}